dot_net_core_uninstaller/__init__.py
dot_net_core_uninstaller/cli.py
dot_net_core_uninstaller-0.3.0.dist-info/LICENSE
dot_net_core_uninstaller-0.3.0.dist-info/METADATA
dot_net_core_uninstaller-0.3.0.dist-info/WHEEL
dot_net_core_uninstaller-0.3.0.dist-info/entry_points.txt
dot_net_core_uninstaller-0.3.0.dist-info/top_level.txt
dot_net_core_uninstaller-0.3.0.dist-info/RECORD
