Metadata-Version: 2.1
Name: dot-net-core-uninstaller
Version: 0.3.0
Summary: Delete previous versions of .Net Core and its runtime files.
Home-page: https://github.com/akshaybabloo/uninstall-dot-net-core
Author: Akshay Raj Gollahalli
Author-email: akshay@gollahalli.com
License: MIT
Keywords: uninstaller,.net core uninstaller,.net core
Platform: UNKNOWN
Classifier: License :: OSI Approved :: MIT License
Classifier: Operating System :: OS Independent
Classifier: Programming Language :: Python :: 3 :: Only
Classifier: Programming Language :: Python :: 3.6
Classifier: Programming Language :: Python :: 3.7
Classifier: Intended Audience :: Developers
Classifier: Environment :: Console
Classifier: Development Status :: 4 - Beta
Classifier: Topic :: Utilities
Requires-Dist: click (==7.0)
Requires-Dist: tabulate (==0.8.3)
